README.rst
setup.py
ubuild
ubuild.bat
ubuild.py
ubuild.egg-info/PKG-INFO
ubuild.egg-info/SOURCES.txt
ubuild.egg-info/dependency_links.txt
ubuild.egg-info/requires.txt
ubuild.egg-info/top_level.txt