Metadata-Version: 1.1
Name: ubuild
Version: 0.2.0
Summary: A no-frills build script framework.
Home-page: https://github.com/jeffrimko/Ubuild
Author: Jeff Rimko
Author-email: jeffrimko@gmail.com
License: MIT
Keywords: cli menu
Platform: UNKNOWN
Classifier: Development Status :: 4 - Beta
Classifier: Topic :: Utilities
Classifier: Programming Language :: Python :: 2.7
Classifier: Programming Language :: Python :: 3
